clockfy_seon_sspo_etl/__init__.py
clockfy_seon_sspo_etl/atomic_software_project.py
clockfy_seon_sspo_etl/complex_software_project.py
clockfy_seon_sspo_etl/factories.py
clockfy_seon_sspo_etl/scrum_performed_task.py
clockfy_seon_sspo_etl/stakeholder_participation.py
clockfy_seon_sspo_etl/team_member.py
clockfy_seon_sspo_etl/services/__init__.py
clockfy_seon_sspo_etl/services/abstract_service.py
clockfy_seon_sspo_etl/services/factories.py
clockfy_seon_sspo_etl/services/project_service.py
clockfy_seon_sspo_etl/services/task_service.py
clockfy_seon_sspo_etl/services/team_member_service.py
clockfy_seon_sspo_etl/services/time_entry_service.py
clockfy_seon_sspo_etl/services/workspace_service.py
clockify_seon_sspo_etl-2.0.0.dist-info/METADATA
clockify_seon_sspo_etl-2.0.0.dist-info/WHEEL
clockify_seon_sspo_etl-2.0.0.dist-info/top_level.txt
clockify_seon_sspo_etl-2.0.0.dist-info/RECORD
